{
  "camera": {
    "kind": "ortho",
    "position": [0, 4, 8],
    "target": [0, 0, 0],
    "up": [0, 1, 0],
    "width": 12,
    "height": 8
  },
  "objects": [
    {
      "kind": "plane",
      "point": [-3, 0, 0],
      "normal": [0, 1, 0],
      "material": {
        "color": "#FFFFFF",
        "ambient": 0.2,
        "diffuse": 0.8,
        "specular": 0.1,
        "shininess": 10,
        "texture": {
          "type": "grid",
          "line_color": "#FF0000",
          "line_width": 0.02,
          "cell_size": 0.3
        }
      }
    },
    {
      "kind": "plane",
      "point": [0, 0, 0],
      "normal": [0, 1, 0],
      "material": {
        "color": "#FFFFFF",
        "ambient": 0.2,
        "diffuse": 0.8,
        "specular": 0.1,
        "shininess": 10,
        "texture": {
          "type": "grid",
          "line_color": "#333333",
          "line_width": 0.05,
          "cell_size": 0.8
        }
      }
    },
    {
      "kind": "plane",
      "point": [3, 0, 0],
      "normal": [0, 1, 0],
      "material": {
        "color": "#FFFFFF",
        "ambient": 0.2,
        "diffuse": 0.8,
        "specular": 0.1,
        "shininess": 10,
        "texture": {
          "type": "grid",
          "line_color": "#0066CC",
          "line_width": 0.1,
          "cell_size": 1.2
        }
      }
    }
  ],
  "lights": [
    {
      "position": [0, 4, 6],
      "color": "#FFFFFF",
      "intensity": 1.0
    }
  ],
  "scene_settings": {
    "ambient_illumination": {
      "color": "#FFFFFF",
      "intensity": 0.15
    },
    "background_color": "#4488CC"
  }
}